LICENSE
MANIFEST.in
README.md
requirements.txt
setup.py
tox.ini
django_form_extensions.egg-info/PKG-INFO
django_form_extensions.egg-info/SOURCES.txt
django_form_extensions.egg-info/dependency_links.txt
django_form_extensions.egg-info/not-zip-safe
django_form_extensions.egg-info/requires.txt
django_form_extensions.egg-info/top_level.txt
docs/HTMLField.md
form_extensions/__init__.py
form_extensions/fields.py
form_extensions/forms.py
form_extensions/utils.py
form_extensions/widgets.py