Metadata-Version: 1.0
Name: django-form-extensions
Version: 0.1.2b4
Summary: Useful fields and widgets for Django forms.
Home-page: https://bitbucket.org/nextscreenlabs/django-form-extensions
Author: Jason Christa
Author-email: jason@zeitcode.com
License: Copyright (c) 2012 Jason Christa and contributors
